annieslasso-0.2.96.dist-info/licenses/LICENSE
thecannon/__init__.py
thecannon/__main__.py
thecannon/censoring.py
thecannon/continuum.py
thecannon/fitting.py
thecannon/model.py
thecannon/plot.py
thecannon/restricted.py
thecannon/utils.py
thecannon/tests/__init__.py
thecannon/tests/test_utils.py
thecannon/vectorizer/__init__.py
thecannon/vectorizer/base.py
thecannon/vectorizer/polynomial.py
annieslasso-0.2.96.dist-info/METADATA
annieslasso-0.2.96.dist-info/WHEEL
annieslasso-0.2.96.dist-info/entry_points.txt
annieslasso-0.2.96.dist-info/top_level.txt
annieslasso-0.2.96.dist-info/RECORD
